qb_core/common/base_model.py
qb_core/common/plugin/plugin_manager.py
qb_core/event_bus/event_bus_core.py
qb_core/event_bus/event_bus_default.py
qb_core/event_bus/event_bus_events.py
qb_core/event_bus/event_bus_interface.py
qb_core/ocra_pkg/ocra.py
qb_core/ocra_pkg/customer/_customer_persistence.py
qb_core/ocra_pkg/customer/customer_entity.py
qb_core/ocra_pkg/customer/customer_model.py
qb_core/ocra_pkg/order/_order_persistence.py
qb_core/ocra_pkg/order/order_entity.py
qb_core/ocra_pkg/order/order_model.py
qb_core/oproc_pkg/oproc.py
qb_core/oproc_pkg/cook_assignment/_cook_assignment_persistence.py
qb_core/oproc_pkg/cook_assignment/cook_assignment_entity.py
qb_core/oproc_pkg/cook_assignment/cook_assignment_model.py
qb_core/oproc_pkg/order/_order_persistence.py
qb_core/oproc_pkg/order/order_entity.py
qb_core/oproc_pkg/order/order_model.py
qb_core/rats_pkg/plug_point_config.py
qb_core/rats_pkg/rats.py
qb_core/rats_pkg/cook/cook_entity.py
qb_core/rats_pkg/cook/cook_model.py
qb_core/rats_pkg/cook/cook_persistence_core.py
qb_core/rats_pkg/cook/cook_persistence_plug_point.py
qb_core/rats_pkg/restaurant/_restaurant_persistence.py
qb_core/rats_pkg/restaurant/restaurant_entity.py
qb_core/rats_pkg/restaurant/restaurant_model.py
qb_core/rats_pkg/signin/_signin_persistence.py
qb_core/rats_pkg/signin/secure_context.py
qb_core/rats_pkg/signin/signin_service.py
qb_core/rats_pkg/signup/_signup_persistence.py
qb_core/rats_pkg/signup/signup_service.py
qb_core_all-0.0.26.dist-info/LICENSE
qb_core_all-0.0.26.dist-info/METADATA
qb_core_all-0.0.26.dist-info/WHEEL
qb_core_all-0.0.26.dist-info/top_level.txt
qb_core_all-0.0.26.dist-info/RECORD
