Metadata-Version: 2.1
Name: qb-core-all
Version: 0.0.26
Summary: Basic app to demonstrate simple architectural concepts
Author-email: Dinesh Kamath <dmkamath@gmail.com>
Project-URL: Homepage, https://github.com/dmkamath/quick_bytes
Project-URL: Bug Tracker, https://github.com/dmkamath/quick_bytes/issues
Classifier: Programming Language :: Python :: 3
Classifier: License :: OSI Approved :: MIT License
Classifier: Operating System :: OS Independent
Requires-Python: >=3.8
License-File: LICENSE
